hurricane_analysis/__init__.py
hurricane_analysis/analysis.py
hurricane_analysis/pca_calculator.py
hurricane_analysis/utils.py
climate_hurricane_analysis-0.1.2.dist-info/METADATA
climate_hurricane_analysis-0.1.2.dist-info/WHEEL
climate_hurricane_analysis-0.1.2.dist-info/top_level.txt
climate_hurricane_analysis-0.1.2.dist-info/RECORD
